{
  "project_info": {
    "project_number": "915141320252",
    "firebase_url": "https://mobifishtest.firebaseio.com",
    "project_id": "mobifishtest",
    "storage_bucket": "mobifishtest.appspot.com"
  },
  "client": [
    {
      "client_info": {
        "mobilesdk_app_id": "1:915141320252:android:85fcf5d2a0ce69af5a6d39",
        "android_client_info": {
          "package_name": "com.polotechnologies.mobifish"
        }
      },
      "oauth_client": [
        {
          "client_id": "915141320252-1asbd979dog99pccqvpmkttd674c2u55.apps.googleusercontent.com",
          "client_type": 1,
          "android_info": {
            "package_name": "com.polotechnologies.mobifish",
            "certificate_hash": "feb3dd0728b492bea879bf361f1c97d0c17f9724"
          }
        },
        {
          "client_id": "915141320252-sbmt087502vd6fritgmu6qqgr49f5og9.apps.googleusercontent.com",
          "client_type": 3
        }
      ],
      "api_key": [
        {
          "current_key": "AIzaSyA9NqqL_0TT2ERa70OqGGASHCZJ9_yWBt8"
        }
      ],
      "services": {
        "appinvite_service": {
          "other_platform_oauth_client": [
            {
              "client_id": "915141320252-sbmt087502vd6fritgmu6qqgr49f5og9.apps.googleusercontent.com",
              "client_type": 3
            }
          ]
        }
      }
    }
  ],
  "configuration_version": "1"
}